textbook/chap_9/components.vhdl
library IEEE;
use IEEE.std_logic_1164.all;

entity my_and is
	port (A, B: in  std_logic;
	      C:    out std_logic);
end my_and;

architecture and_arch of my_and is
begin
	C <= A AND B;
end and_arch;

library IEEE;
use IEEE.std_logic_1164.all;

entity my_or is
	port (A, B: in  std_logic;
	      C:    out std_logic);
end my_or;

architecture or_arch of my_or is
begin
	C <= A OR B;
end or_arch;

library IEEE;
use IEEE.std_logic_1164.all;

entity my_not is
	port (A: in  std_logic;
	      B:    out std_logic);
end my_not;

architecture not_arch of my_not is
begin
	B <= NOT A;
end not_arch;

library IEEE;
use IEEE.std_logic_1164.all;

entity my_nand is
	port (A, B: in  std_logic;
	      C:    out std_logic);
end my_nand;

architecture nand_arch of my_nand is
begin
	C <= NOT(A AND B);
end nand_arch;

library IEEE;
use IEEE.std_logic_1164.all;

entity my_nnor is
	port (A, B: in  std_logic;
	      C:    out std_logic);
end my_nnor;

architecture nnor_arch of my_nnor is
begin
	C <= NOT(A) OR NOT(B);
end nnor_arch;

textbook/chap_9/3_a.vhdl
library IEEE;
use IEEE.std_logic_1164.all;

entity ex_3_a is
	port(A, B, C: in  std_logic;
	     F:	      out std_logic);
end ex_3_a;

architecture exercise of ex_3_a is
	component my_and
		port(A, B: in  std_logic;
		     C:     out std_logic);
	end component;

	component my_or
		port(A, B: in  std_logic;
		     C:     out std_logic);
	end component;

	signal notA, notB, notC, D, E: std_logic;

begin
	notA <= NOT(A);
	notB <= NOT(B);
	notC <= NOT(C);

	and1: my_and
	port map (A => A, B => notB, C => D);

	and2: my_and
	port map (A => notA, B => notC, C => E);

	or1: my_or
	port map (A => D, B => E, C => F);

end exercise;

textbook/chap_9/3_a_tb.vhdl
library IEEE;
use IEEE.std_logic_1164.all;

entity ex_3_a_tb is
end ex_3_a_tb;

architecture test of ex_3_a_tb is
	component ex_3_a
		port
		(
			A, B, C:    in  std_logic;
	      		F:          out std_logic
		);
	end component;

	signal A, B, C, F: std_logic;

begin
	exercise: ex_3_a port map (A=>A, B=>B, C=>C, F=>F);

	process begin

	A <= 'X';
	B <= 'X';
	C <= 'X';
	wait for 1 ns;

	A <= '1';
	B <= '1';
	C <= '1';
	wait for 1 ns;

	A <= '1';
	B <= '1';
	C <= '0';
	wait for 1 ns;

	A <= '1';
	B <= '0';
	C <= '1';
	wait for 1 ns;

	A <= '1';
	B <= '0';
	C <= '0';
	wait for 1 ns;

	A <= '0';
	B <= '1';
	C <= '1';
	wait for 1 ns;

	A <= '0';
	B <= '1';
	C <= '0';
	wait for 1 ns;

	A <= '0';
	B <= '0';
	C <= '1';
	wait for 1 ns;

	A <= '0';
	B <= '0';
	C <= '0';
	wait for 1 ns;

	assert false report "Reached end of test";
	wait;

	end process;

end test;

textbook/chap_9/3_a.vcd
$date
  Wed Oct 14 19:13:33 2020
$end
$version
  GHDL v0
$end
$timescale
  1 fs
$end
$scope module standard $end
$upscope $end
$scope module std_logic_1164 $end
$upscope $end
$scope module ex_3_a_tb $end
$var reg 1 ! a $end
$var reg 1 " b $end
$var reg 1 # c $end
$var reg 1 $ f $end
$scope module exercise $end
$var reg 1 % a $end
$var reg 1 & b $end
$var reg 1 ' c $end
$var reg 1 ( f $end
$var reg 1 ) nota $end
$var reg 1 * notb $end
$var reg 1 + notc $end
$var reg 1 , d $end
$var reg 1 - e $end
$scope module and1 $end
$var reg 1 . a $end
$var reg 1 / b $end
$var reg 1 0 c $end
$upscope $end
$scope module and2 $end
$var reg 1 1 a $end
$var reg 1 2 b $end
$var reg 1 3 c $end
$upscope $end
$scope module or1 $end
$var reg 1 4 a $end
$var reg 1 5 b $end
$var reg 1 6 c $end
$upscope $end
$upscope $end
$upscope $end
$enddefinitions $end
#0
X!
X"
X#
X$
X%
X&
X'
X(
X)
X*
X+
X,
X-
X.
X/
X0
X1
X2
X3
X4
X5
X6
#1000000
1!
1"
1#
0$
1%
1&
1'
0(
0)
0*
0+
0,
0-
1.
0/
00
01
02
03
04
05
06
#2000000
0#
0'
1+
12
#3000000
0"
1#
1$
0&
1'
1(
1*
0+
1,
1/
10
02
14
16
#4000000
0#
0'
1+
12
#5000000
0!
1"
1#
0$
0%
1&
1'
0(
1)
0*
0+
0,
0.
0/
00
11
02
04
06
#6000000
0#
1$
0'
1(
1+
1-
12
13
15
16
#7000000
0"
1#
0$
0&
1'
0(
1*
0+
0-
1/
02
03
05
06
#8000000
0#
1$
0'
1(
1+
1-
12
13
15
16
