textbook/chap_9/components.vhdl
library IEEE;
use IEEE.std_logic_1164.all;

--these are the components used throughout the exercises for this chapter

--AND gate component--
entity my_and is
	port (A, B: in  std_logic; --two input signals to the gate
	      C:    out std_logic); --output signal
end my_and;

architecture and_arch of my_and is
begin
	C <= A AND B; --A*B=C
end and_arch;

library IEEE;
use IEEE.std_logic_1164.all;

--OR gate component--
entity my_or is
	port (A, B: in  std_logic; --two input signals to the gate
	      C:    out std_logic); --output signal
end my_or;

architecture or_arch of my_or is
begin
	C <= A OR B; --A+B=C
end or_arch;

library IEEE;
use IEEE.std_logic_1164.all;

--OR gate with four inputs--
entity my_4_or is
	port (A, B, C, D: in  std_logic; --four inputs to gate
	      E:          out std_logic); --output signal
end my_4_or;

architecture or_4_arch of my_4_or is
begin
	E <= A OR B OR C OR D; --A+B+C+D=E
end or_4_arch;

library IEEE;
use IEEE.std_logic_1164.all;

--NAND gate component --
entity my_nand is
	port (A, B: in  std_logic; --two input signals
	      C:    out std_logic); --output signal
end my_nand;

architecture nand_arch of my_nand is
begin
	C <= NOT(A AND B); --(AB)'=C
end nand_arch;

library IEEE;
use IEEE.std_logic_1164.all;

--OR gate with input signals inversed--
entity my_nnor is
	port (A, B: in  std_logic; --two input signals
	      C:    out std_logic); --output signal
end my_nnor;

architecture nnor_arch of my_nnor is
begin
	C <= NOT(A) OR NOT(B); --A'+B'=C
end nnor_arch;

library IEEE;
use IEEE.std_logic_1164.all;

--3:8 decoder--
entity my_decode_3_8 is
	port (A, B, C: in  std_logic; --3 1-bit input signals
	      D:       out std_logic_vector(7 downto 0)); --8-bit output signal
end my_decode_3_8;

architecture decode_3_8_arch of my_decode_3_8 is
	signal SEL: std_logic_vector (2 downto 0); --3-bit selection signal
begin
	SEL <= A & B & C; --concatonate A, B, and C into selection signal (SEL)

	--select output D based on SEL
	with SEL select
	D <= "10000000" when "111",
	     "01000000" when "110",
	     "00100000" when "101",
	     "00010000" when "100",
	     "00001000" when "011",
	     "00000100" when "010",
	     "00000010" when "001",
	     "00000001" when "000",
	     "00000000" when others;	
end decode_3_8_arch;

textbook/chap_9/3_c.vhdl
library IEEE;
use IEEE.std_logic_1164.all;

entity ex_3_c is
	port(A, B, C: in  std_logic;
	     F:	      out std_logic);
end ex_3_c;

architecture exercise of ex_3_c is

	component my_and
		port(A, B: in  std_logic;
		     C:    out std_logic);
	end component;

	component my_or
		port(A, B: in  std_logic;
		     C:    out std_logic);
	end component;

	signal notB, notC, D, E: std_logic;
begin

	notB <= NOT B;
	notC <= NOT C;

	and1: my_and
	port map (A => A, B => C, C => D);

	and2: my_and
	port map (A => notC, B => notB, C => E);

	or1: my_or
	port map (A => D, B => E, C => F);

end exercise;

textbook/chap_9/3_c_tb.vhdl
library IEEE;
use IEEE.std_logic_1164.all;

entity ex_3_c_tb is
end ex_3_c_tb;

architecture test of ex_3_c_tb is
	component ex_3_c
		port
		(
			A, B, C:    in  std_logic;
	      		F:          out std_logic
		);
	end component;

	signal A, B, C, F: std_logic;

begin
	exercise: ex_3_c port map (A=>A, B=>B, C=>C, F=>F);

	process begin

	A <= 'X';
	B <= 'X';
	C <= 'X';
	wait for 1 ns;

	A <= '1';
	B <= '1';
	C <= '1';
	wait for 1 ns;

	A <= '1';
	B <= '1';
	C <= '0';
	wait for 1 ns;

	A <= '1';
	B <= '0';
	C <= '1';
	wait for 1 ns;

	A <= '1';
	B <= '0';
	C <= '0';
	wait for 1 ns;

	A <= '0';
	B <= '1';
	C <= '1';
	wait for 1 ns;

	A <= '0';
	B <= '1';
	C <= '0';
	wait for 1 ns;

	A <= '0';
	B <= '0';
	C <= '1';
	wait for 1 ns;

	A <= '0';
	B <= '0';
	C <= '0';
	wait for 1 ns;

	assert false report "Reached end of test";
	wait;

	end process;

end test;

textbook/chap_9/3_c.vcd
$date
  Wed Oct 14 19:47:31 2020
$end
$version
  GHDL v0
$end
$timescale
  1 fs
$end
$scope module standard $end
$upscope $end
$scope module std_logic_1164 $end
$upscope $end
$scope module ex_3_c_tb $end
$var reg 1 ! a $end
$var reg 1 " b $end
$var reg 1 # c $end
$var reg 1 $ f $end
$scope module exercise $end
$var reg 1 % a $end
$var reg 1 & b $end
$var reg 1 ' c $end
$var reg 1 ( f $end
$var reg 1 ) notb $end
$var reg 1 * notc $end
$var reg 1 + d $end
$var reg 1 , e $end
$scope module and1 $end
$var reg 1 - a $end
$var reg 1 . b $end
$var reg 1 / c $end
$upscope $end
$scope module and2 $end
$var reg 1 0 a $end
$var reg 1 1 b $end
$var reg 1 2 c $end
$upscope $end
$scope module or1 $end
$var reg 1 3 a $end
$var reg 1 4 b $end
$var reg 1 5 c $end
$upscope $end
$upscope $end
$upscope $end
$enddefinitions $end
#0
X!
X"
X#
X$
X%
X&
X'
X(
X)
X*
X+
X,
X-
X.
X/
X0
X1
X2
X3
X4
X5
#1000000
1!
1"
1#
1$
1%
1&
1'
1(
0)
0*
1+
0,
1-
1.
1/
00
01
02
13
04
15
#2000000
0#
0$
0'
0(
1*
0+
0.
0/
10
03
05
#3000000
0"
1#
1$
0&
1'
1(
1)
0*
1+
1.
1/
00
11
13
15
#4000000
0#
1$
0'
1(
1*
0+
1,
0.
0/
10
12
03
14
15
#5000000
0!
1"
1#
0$
0%
1&
1'
0(
0)
0*
0,
0-
1.
00
01
02
04
05
#6000000
0#
0'
1*
0.
10
#7000000
0"
1#
0&
1'
1)
0*
1.
00
11
#8000000
0#
1$
0'
1(
1*
1,
0.
10
12
14
15
