textbook/chap_9/components.vhdl
library IEEE;
use IEEE.std_logic_1164.all;

entity my_and is
	port (A, B: in  std_logic;
	      C:    out std_logic);
end my_and;

architecture and_arch of my_and is
begin
	C <= A AND B;
end and_arch;

library IEEE;
use IEEE.std_logic_1164.all;

entity my_or is
	port (A, B: in  std_logic;
	      C:    out std_logic);
end my_or;

architecture or_arch of my_or is
begin
	C <= A OR B;
end or_arch;

library IEEE;
use IEEE.std_logic_1164.all;

entity my_4_or is
	port (A, B, C, D: in  std_logic;
	      E:          out std_logic);
end my_4_or;

architecture or_4_arch of my_4_or is
begin
	E <= A OR B OR C OR D;
end or_4_arch;

library IEEE;
use IEEE.std_logic_1164.all;

entity my_nand is
	port (A, B: in  std_logic;
	      C:    out std_logic);
end my_nand;

architecture nand_arch of my_nand is
begin
	C <= NOT(A AND B);
end nand_arch;

library IEEE;
use IEEE.std_logic_1164.all;

entity my_nnor is
	port (A, B: in  std_logic;
	      C:    out std_logic);
end my_nnor;

architecture nnor_arch of my_nnor is
begin
	C <= NOT(A) OR NOT(B);
end nnor_arch;

library IEEE;
use IEEE.std_logic_1164.all;

entity my_decode_3_8 is
	port (A, B, C: in  std_logic;
	      D:       out std_logic_vector(7 downto 0));
end my_decode_3_8;

architecture decode_3_8_arch of my_decode_3_8 is
	signal SEL: std_logic_vector (2 downto 0);
begin
	SEL <= A & B & C;

	with SEL select
	D <= "10000000" when "111",
	     "01000000" when "110",
	     "00100000" when "101",
	     "00010000" when "100",
	     "00001000" when "011",
	     "00000100" when "010",
	     "00000010" when "001",
	     "00000001" when "000",
	     "00000000" when others;	
end decode_3_8_arch;

textbook/chap_9/3_d.vhdl
library IEEE;
use IEEE.std_logic_1164.all;

entity ex_3_d is
	port(A, B, C: in  std_logic;
	     F:	      out std_logic);
end ex_3_d;

architecture exercise of ex_3_d is

	component my_nand
		port(A, B: in  std_logic;
		     C:    out std_logic);
	end component;

	component my_nnor
		port(A, B: in  std_logic;
		     C:    out std_logic);
	end component;

	signal notA, notC, D, E: std_logic;
begin

	notA <= NOT A;
	notC <= NOT C;

	nand1: my_nand
	port map (A => notA, B => notC, C => D);

	nand2: my_nand
	port map (A => A, B => B, C => E);

	nnor1: my_nnor
	port map (A => D, B => E, C => F);

end exercise;

textbook/chap_9/3_d_tb.vhdl
library IEEE;
use IEEE.std_logic_1164.all;

entity ex_3_d_tb is
end ex_3_d_tb;

architecture test of ex_3_d_tb is
	component ex_3_d
		port
		(
			A, B, C:    in  std_logic;
	      		F:          out std_logic
		);
	end component;

	signal A, B, C, F: std_logic;

begin
	exercise: ex_3_d port map (A=>A, B=>B, C=>C, F=>F);

	process begin

	A <= 'X';
	B <= 'X';
	C <= 'X';
	wait for 1 ns;

	A <= '1';
	B <= '1';
	C <= '1';
	wait for 1 ns;

	A <= '1';
	B <= '1';
	C <= '0';
	wait for 1 ns;

	A <= '1';
	B <= '0';
	C <= '1';
	wait for 1 ns;

	A <= '1';
	B <= '0';
	C <= '0';
	wait for 1 ns;

	A <= '0';
	B <= '1';
	C <= '1';
	wait for 1 ns;

	A <= '0';
	B <= '1';
	C <= '0';
	wait for 1 ns;

	A <= '0';
	B <= '0';
	C <= '1';
	wait for 1 ns;

	A <= '0';
	B <= '0';
	C <= '0';
	wait for 1 ns;

	assert false report "Reached end of test";
	wait;

	end process;

end test;

textbook/chap_9/3_d.vcd
$date
  Wed Oct 14 19:51:35 2020
$end
$version
  GHDL v0
$end
$timescale
  1 fs
$end
$scope module standard $end
$upscope $end
$scope module std_logic_1164 $end
$upscope $end
$scope module ex_3_d_tb $end
$var reg 1 ! a $end
$var reg 1 " b $end
$var reg 1 # c $end
$var reg 1 $ f $end
$scope module exercise $end
$var reg 1 % a $end
$var reg 1 & b $end
$var reg 1 ' c $end
$var reg 1 ( f $end
$var reg 1 ) nota $end
$var reg 1 * notc $end
$var reg 1 + d $end
$var reg 1 , e $end
$scope module nand1 $end
$var reg 1 - a $end
$var reg 1 . b $end
$var reg 1 / c $end
$upscope $end
$scope module nand2 $end
$var reg 1 0 a $end
$var reg 1 1 b $end
$var reg 1 2 c $end
$upscope $end
$scope module nnor1 $end
$var reg 1 3 a $end
$var reg 1 4 b $end
$var reg 1 5 c $end
$upscope $end
$upscope $end
$upscope $end
$enddefinitions $end
#0
X!
X"
X#
X$
X%
X&
X'
X(
X)
X*
X+
X,
X-
X.
X/
X0
X1
X2
X3
X4
X5
#1000000
1!
1"
1#
1$
1%
1&
1'
1(
0)
0*
1+
0,
0-
0.
1/
10
11
02
13
04
15
#2000000
0#
0'
1*
1.
#3000000
0"
1#
0$
0&
1'
0(
0*
1,
0.
01
12
14
05
#4000000
0#
0'
1*
1.
#5000000
0!
1"
1#
0%
1&
1'
1)
0*
1-
0.
00
11
#6000000
0#
1$
0'
1(
1*
0+
1.
0/
03
15
#7000000
0"
1#
0$
0&
1'
0(
0*
1+
0.
1/
01
13
05
#8000000
0#
1$
0'
1(
1*
0+
1.
0/
03
15
