textbook/chap_8/10.vhdl
library IEEE;
use IEEE.std_logic_1164.all;

entity fsm_10 is
	port( X, CLK:    in  std_logic;
	      Z:	 out std_logic;
	      Y:	 out std_logic_vector (2 downto 0));
end fsm_10;

architecture exercise of fsm_10 is
	type state_type is (A, B, C);
	signal PS, NS: state_type;

begin
	sync_proc: process (CLK, NS)
	begin
		if(rising_edge(CLK)) then PS <= NS;
		end if;
	end process sync_proc;

	comb_proc: process (PS, X)
	begin
		Z <= '0';
		case PS is
			when A =>
				Z <= '1';
				NS <= B;

			when B =>
				if(X = '0') then
					Z <= '0';
					NS <= A;
				else
					Z <= '0';
					NS <= C;
				end if;	

			when C =>
				Z <= '1';
				NS <= A;

			when others =>
				Z <= '0';
				NS <= A;
		end case;
	end process comb_proc;

	with PS select
		Y <= "100" when A,
		     "010" when B,
		     "001" when C,
		     "000" when others;
end exercise;

--NOTE: Assuming typo so X' goes from B to A

textbook/chap_8/10_tb.vhdl
library IEEE;
use IEEE.std_logic_1164.all;

entity ex_10_tb is
end ex_10_tb;

architecture test of ex_10_tb is
	component fsm_10
		port
		(
			X, CLK:  in  std_logic;
	      		Z:	 out std_logic;
	      		Y:	 out std_logic_vector (2 downto 0)
		);
	end component;

	signal X, CLK, Z: std_logic;
	signal Y: std_logic_vector (2 downto 0);

begin
	exercise: fsm_10 port map (X => X, CLK => CLK, Z => Z, Y => Y);

	process begin

--A
	X <= '0';
	CLK <= '0';
	wait for 1 ns;

	CLK <= '1';
	wait for 1 ns;

	CLK <= '0';
	wait for 1 ns;

--B
	X <= '0';
	CLK <= '0';
	wait for 1 ns;

	CLK <= '1';
	wait for 1 ns;

	CLK <= '0';
	wait for 1 ns;

--A
	X <= '1';
	CLK <= '0';
	wait for 1 ns;

	CLK <= '1';
	wait for 1 ns;

	CLK <= '0';
	wait for 1 ns;

--B
	X <= '1';
	CLK <= '0';
	wait for 1 ns;

	CLK <= '1';
	wait for 1 ns;

	CLK <= '0';
	wait for 1 ns;

--C
	X <= '0';
	CLK <= '0';
	wait for 1 ns;

	CLK <= '1';
	wait for 1 ns;

	CLK <= '0';
	wait for 1 ns;

--A
	X <= '0';
	CLK <= '0';
	wait for 1 ns;

	CLK <= '1';
	wait for 1 ns;

	CLK <= '0';
	wait for 1 ns;

--B
	X <= '1';
	CLK <= '0';
	wait for 1 ns;

	CLK <= '1';
	wait for 1 ns;

	CLK <= '0';
	wait for 1 ns;

--C
	X <= '1';
	CLK <= '0';
	wait for 1 ns;

	CLK <= '1';
	wait for 1 ns;

	CLK <= '0';
	wait for 1 ns;

	assert false report "Reached end of test";
	wait;

	end process;

end test;

textbook/chap_8/10.vcd
$date
  Tue Sep 29 21:46:23 2020
$end
$version
  GHDL v0
$end
$timescale
  1 fs
$end
$scope module standard $end
$upscope $end
$scope module std_logic_1164 $end
$upscope $end
$scope module ex_10_tb $end
$var reg 1 ! x $end
$var reg 1 " clk $end
$var reg 1 # z $end
$var reg 3 $ y[2:0] $end
$scope module exercise $end
$var reg 1 % x $end
$var reg 1 & clk $end
$var reg 1 ' z $end
$var reg 3 ( y[2:0] $end
$comment ps is not handled $end
$comment ns is not handled $end
$upscope $end
$upscope $end
$enddefinitions $end
#0
0!
0"
1#
b100 $
0%
0&
1'
b100 (
#1000000
1"
0#
b010 $
1&
0'
b010 (
#2000000
0"
0&
#3000000
#4000000
1"
1#
b100 $
1&
1'
b100 (
#5000000
0"
0&
#6000000
1!
1%
1'
#7000000
1"
0#
b010 $
1&
0'
b010 (
#8000000
0"
0&
#9000000
#10000000
1"
1#
b001 $
1&
1'
b001 (
#11000000
0"
0&
#12000000
0!
0%
1'
#13000000
1"
b100 $
1&
1'
b100 (
#14000000
0"
0&
#15000000
#16000000
1"
0#
b010 $
1&
0'
b010 (
#17000000
0"
0&
#18000000
1!
1%
#19000000
1"
1#
b001 $
1&
1'
b001 (
#20000000
0"
0&
#21000000
#22000000
1"
b100 $
1&
1'
b100 (
