textbook/chap_8/12.vhdl
library IEEE;
use IEEE.std_logic_1164.all;

entity fsm_12 is
	port( X1, X2, CLK:    in  std_logic;
	      Z1, Z2:	      out std_logic;
	      Y:	      out std_logic_vector (1 downto 0));
end fsm_12;

architecture exercise of fsm_12 is
	type state_type is (A, B, C);
	signal PS, NS: state_type;

begin
	sync_proc: process (CLK, NS)
	begin
		if(rising_edge(CLK)) then PS <= NS;
		end if;
	end process sync_proc;

	comb_proc: process (PS, X1, X2)
	begin
		Z1 <= '0';
		Z2 <= '0';
		case PS is
			when A =>
				Z2 <= '1';

				if(X1 = '0') then
					Z1 <= '0';
					NS <= A;
				else
					Z1 <= '1';
					NS <= B;
				end if;	

			when B =>
				Z2 <= '0';

				if(X2 = '0') then
					Z1 <= '1';
					NS <= C;
				else
					Z1 <= '0';
					NS <= A;
				end if;	

			when C =>
				Z2 <= '1';

				if(X2 = '0') then
					Z1 <= '0';
					NS <= A;
				else
					Z1 <= '1';
					NS <= C;
				end if;	

			when others =>
				Z1 <= '0';
				Z2 <= '0';
				NS <= A;
		end case;
	end process comb_proc;

	with PS select
		Y <= "11" when A,
		     "01" when B,
		     "00" when C,
		     "00" when others;
end exercise;

--NOT: Assuming typo and X1/X2 inputs

textbook/chap_8/12_tb.vhdl
library IEEE;
use IEEE.std_logic_1164.all;

entity ex_12_tb is
end ex_12_tb;

architecture test of ex_12_tb is
	component fsm_12
		port
		(
			X1, X2, CLK:  in  std_logic;
	      		Z1, Z2:	      out std_logic;
	      		Y:	      out std_logic_vector (1 downto 0)
		);
	end component;

	signal X1, X2, CLK, Z1, Z2: std_logic;
	signal Y: std_logic_vector (1 downto 0);

begin
	exercise: fsm_12 port map (X1 => X1, X2 => X2, CLK => CLK, Z1 => Z1, Z2 => Z2, Y => Y);

	process begin

--A
	X1 <= 'X';
	X2 <= 'X';
	CLK <= '0';
	wait for 1 ns;

--A
	X1 <= '0';
	X2 <= 'X';
	CLK <= '0';
	wait for 1 ns;

	CLK <= '1';
	wait for 1 ns;

	CLK <= '0';
	wait for 1 ns;

--B
	X1 <= '1';
	X2 <= 'X';
	CLK <= '0';
	wait for 1 ns;

	CLK <= '1';
	wait for 1 ns;

	CLK <= '0';
	wait for 1 ns;

--A
	X1 <= 'X';
	X2 <= '1';
	CLK <= '0';
	wait for 1 ns;

	CLK <= '1';
	wait for 1 ns;

	CLK <= '0';
	wait for 1 ns;

--A
	X1 <= '1';
	X2 <= 'X';
	CLK <= '0';
	wait for 1 ns;

	CLK <= '1';
	wait for 1 ns;

	CLK <= '0';
	wait for 1 ns;

--B
	X1 <= 'X';
	X2 <= '0';
	CLK <= '0';
	wait for 1 ns;

	CLK <= '1';
	wait for 1 ns;

	CLK <= '0';
	wait for 1 ns;

--C
	X1 <= 'X';
	X2 <= '1';
	CLK <= '0';
	wait for 1 ns;

	CLK <= '1';
	wait for 1 ns;

	CLK <= '0';
	wait for 1 ns;

--C
	X1 <= 'X';
	X2 <= '0';
	CLK <= '0';
	wait for 1 ns;

	CLK <= '1';
	wait for 1 ns;

	CLK <= '0';
	wait for 1 ns;

	assert false report "Reached end of test";
	wait;

	end process;

end test;

textbook/chap_8/12.vcd
$date
  Tue Sep 29 22:20:46 2020
$end
$version
  GHDL v0
$end
$timescale
  1 fs
$end
$scope module standard $end
$upscope $end
$scope module std_logic_1164 $end
$upscope $end
$scope module ex_12_tb $end
$var reg 1 ! x1 $end
$var reg 1 " x2 $end
$var reg 1 # clk $end
$var reg 1 $ z1 $end
$var reg 1 % z2 $end
$var reg 2 & y[1:0] $end
$scope module exercise $end
$var reg 1 ' x1 $end
$var reg 1 ( x2 $end
$var reg 1 ) clk $end
$var reg 1 * z1 $end
$var reg 1 + z2 $end
$var reg 2 , y[1:0] $end
$comment ps is not handled $end
$comment ns is not handled $end
$upscope $end
$upscope $end
$enddefinitions $end
#0
X!
X"
0#
1$
1%
b11 &
X'
X(
0)
1*
1+
b11 ,
#1000000
0!
0$
0'
0*
1+
#2000000
1#
1)
#3000000
0#
0)
#4000000
1!
1$
1'
1*
1+
#5000000
1#
0$
0%
b01 &
1)
0*
0+
b01 ,
#6000000
0#
0)
#7000000
X!
1"
X'
1(
#8000000
1#
1$
1%
b11 &
1)
1*
1+
b11 ,
#9000000
0#
0)
#10000000
1!
X"
1'
X(
1*
1+
#11000000
1#
0$
0%
b01 &
1)
0*
0+
b01 ,
#12000000
0#
0)
#13000000
X!
0"
1$
X'
0(
1*
#14000000
1#
0$
1%
b00 &
1)
0*
1+
b00 ,
#15000000
0#
0)
#16000000
1"
1$
1(
1*
1+
#17000000
1#
1)
#18000000
0#
0)
#19000000
0"
0$
0(
0*
1+
#20000000
1#
1$
b11 &
1)
1*
1+
b11 ,
