textbook/chap_8/8.vhdl
library IEEE;
use IEEE.std_logic_1164.all;

entity fsm_8 is
	port( X, CLK:    in  std_logic;
	      Z1, Z2:    out std_logic;
	      Y:	 out std_logic_vector (2 downto 0));
end fsm_8;

architecture exercise of fsm_8 is
	type state_type is (A, B, C, D, E, F, G, H);
	signal PS, NS: state_type;

begin
	sync_proc: process (CLK, NS)
	begin
		if(rising_edge(CLK)) then PS <= NS;
		end if;
	end process sync_proc;

	comb_proc: process (PS, X)
	begin
		Z1 <= '0';
		Z2 <= '0';
		case PS is
			when A =>
				Z1 <= '0';
				Z2 <= '0';

				if(X = '0') then
					NS <= A;
				else
					NS <= B;
				end if;

			when B =>
				Z1 <= '0';
				Z2 <= '0';

				if(X = '0') then
					NS <= B;
				else
					NS <= C;
				end if;

			when C =>
				Z1 <= '0';
				Z2 <= '0';

				if(X = '0') then
					NS <= C;
				else
					NS <= D;
				end if;

			when D =>
				Z1 <= '1';
				Z2 <= '0';

				if(X = '0') then
					NS <= D;
				else
					NS <= E;
				end if;

			when E =>
				Z1 <= '0';
				Z2 <= '1';

				if(X = '0') then
					NS <= A;
				else
					NS <= F;
				end if;

			when F =>
				Z1 <= '1';
				Z2 <= '1';

				if(X = '0') then
					NS <= F;
				else
					NS <= G;
				end if;

			when G =>
				Z1 <= '1';
				Z2 <= '1';

				if(X = '0') then
					NS <= G;
				else
					NS <= H;
				end if;

			when H =>
				Z1 <= '1';
				Z2 <= '1';

				if(X = '0') then
					NS <= H;
				else
					NS <= A;
				end if;

			when others =>
				Z1 <= '0';
				Z2 <= '0';
				NS <= A;
		end case;
	end process comb_proc;

	with PS select
		Y <= "000" when A,
		     "001" when B,
		     "010" when C,
		     "011" when D,
		     "100" when E,
		     "101" when F,
		     "110" when G,
		     "111" when H,
		     "000" when others;
end exercise;

textbook/chap_8/8_tb.vhdl
library IEEE;
use IEEE.std_logic_1164.all;

entity ex_8_tb is
end ex_8_tb;

architecture test of ex_8_tb is
	component fsm_8
		port
		(
			X, CLK:    in  std_logic;
	      		Z1, Z2:    out std_logic;
	      		Y:	   out std_logic_vector (2 downto 0)
		);
	end component;

	signal X, CLK, Z1, Z2: std_logic;
	signal Y: std_logic_vector (2 downto 0);

begin
	exercise: fsm_8 port map (X => X, CLK => CLK, Z1 => Z1, Z2 => Z2, Y => Y);

	process begin

--A
	X <= '0';
	CLK <= '0';
	wait for 1 ns;

	CLK <= '1';
	wait for 1 ns;

	CLK <= '0';
	wait for 1 ns;

	X <= '1';
	CLK <= '0';
	wait for 1 ns;

	CLK <= '1';
	wait for 1 ns;

	CLK <= '0';
	wait for 1 ns;

--B
	X <= '0';
	CLK <= '0';
	wait for 1 ns;

	CLK <= '1';
	wait for 1 ns;

	CLK <= '0';
	wait for 1 ns;

	X <= '1';
	CLK <= '0';
	wait for 1 ns;

	CLK <= '1';
	wait for 1 ns;

	CLK <= '0';
	wait for 1 ns;

--C
	X <= '0';
	CLK <= '0';
	wait for 1 ns;

	CLK <= '1';
	wait for 1 ns;

	CLK <= '0';
	wait for 1 ns;

	X <= '1';
	CLK <= '0';
	wait for 1 ns;

	CLK <= '1';
	wait for 1 ns;

	CLK <= '0';
	wait for 1 ns;

--D
	X <= '0';
	CLK <= '0';
	wait for 1 ns;

	CLK <= '1';
	wait for 1 ns;

	CLK <= '0';
	wait for 1 ns;

	X <= '1';
	CLK <= '0';
	wait for 1 ns;

	CLK <= '1';
	wait for 1 ns;

	CLK <= '0';
	wait for 1 ns;

--E
	X <= '0';
	CLK <= '0';
	wait for 1 ns;

	CLK <= '1';
	wait for 1 ns;

	CLK <= '0';
	wait for 1 ns;

--A
	X <= '0';
	CLK <= '0';
	wait for 1 ns;

	CLK <= '1';
	wait for 1 ns;

	CLK <= '0';
	wait for 1 ns;

	X <= '1';
	CLK <= '0';
	wait for 1 ns;

	CLK <= '1';
	wait for 1 ns;

	CLK <= '0';
	wait for 1 ns;

--B
	X <= '0';
	CLK <= '0';
	wait for 1 ns;

	CLK <= '1';
	wait for 1 ns;

	CLK <= '0';
	wait for 1 ns;

	X <= '1';
	CLK <= '0';
	wait for 1 ns;

	CLK <= '1';
	wait for 1 ns;

	CLK <= '0';
	wait for 1 ns;

--C
	X <= '0';
	CLK <= '0';
	wait for 1 ns;

	CLK <= '1';
	wait for 1 ns;

	CLK <= '0';
	wait for 1 ns;

	X <= '1';
	CLK <= '0';
	wait for 1 ns;

	CLK <= '1';
	wait for 1 ns;

	CLK <= '0';
	wait for 1 ns;

--D
	X <= '0';
	CLK <= '0';
	wait for 1 ns;

	CLK <= '1';
	wait for 1 ns;

	CLK <= '0';
	wait for 1 ns;

	X <= '1';
	CLK <= '0';
	wait for 1 ns;

	CLK <= '1';
	wait for 1 ns;

	CLK <= '0';
	wait for 1 ns;

--E
	X <= '1';
	CLK <= '0';
	wait for 1 ns;

	CLK <= '1';
	wait for 1 ns;

	CLK <= '0';
	wait for 1 ns;

--F
	X <= '0';
	CLK <= '0';
	wait for 1 ns;

	CLK <= '1';
	wait for 1 ns;

	CLK <= '0';
	wait for 1 ns;

	X <= '1';
	CLK <= '0';
	wait for 1 ns;

	CLK <= '1';
	wait for 1 ns;

	CLK <= '0';
	wait for 1 ns;

--G
	X <= '0';
	CLK <= '0';
	wait for 1 ns;

	CLK <= '1';
	wait for 1 ns;

	CLK <= '0';
	wait for 1 ns;

	X <= '1';
	CLK <= '0';
	wait for 1 ns;

	CLK <= '1';
	wait for 1 ns;

	CLK <= '0';
	wait for 1 ns;

--H
	X <= '0';
	CLK <= '0';
	wait for 1 ns;

	CLK <= '1';
	wait for 1 ns;

	CLK <= '0';
	wait for 1 ns;

	X <= '1';
	CLK <= '0';
	wait for 1 ns;

	CLK <= '1';
	wait for 1 ns;

	CLK <= '0';
	wait for 1 ns;

	assert false report "Reached end of test";
	wait;

	end process;

end test;

textbook/chap_8/8.vcd
$date
  Tue Sep 29 21:21:27 2020
$end
$version
  GHDL v0
$end
$timescale
  1 fs
$end
$scope module standard $end
$upscope $end
$scope module std_logic_1164 $end
$upscope $end
$scope module ex_8_tb $end
$var reg 1 ! x $end
$var reg 1 " clk $end
$var reg 1 # z1 $end
$var reg 1 $ z2 $end
$var reg 3 % y[2:0] $end
$scope module exercise $end
$var reg 1 & x $end
$var reg 1 ' clk $end
$var reg 1 ( z1 $end
$var reg 1 ) z2 $end
$var reg 3 * y[2:0] $end
$comment ps is not handled $end
$comment ns is not handled $end
$upscope $end
$upscope $end
$enddefinitions $end
#0
0!
0"
0#
0$
b000 %
0&
0'
0(
0)
b000 *
#1000000
1"
1'
#2000000
0"
0'
#3000000
1!
1&
#4000000
1"
b001 %
1'
b001 *
#5000000
0"
0'
#6000000
0!
0&
#7000000
1"
1'
#8000000
0"
0'
#9000000
1!
1&
#10000000
1"
b010 %
1'
b010 *
#11000000
0"
0'
#12000000
0!
0&
#13000000
1"
1'
#14000000
0"
0'
#15000000
1!
1&
#16000000
1"
1#
b011 %
1'
1(
b011 *
#17000000
0"
0'
#18000000
0!
0&
1(
#19000000
1"
1'
#20000000
0"
0'
#21000000
1!
1&
1(
#22000000
1"
0#
1$
b100 %
1'
0(
1)
b100 *
#23000000
0"
0'
#24000000
0!
0&
1)
#25000000
1"
0$
b000 %
1'
0)
b000 *
#26000000
0"
0'
#27000000
#28000000
1"
1'
#29000000
0"
0'
#30000000
1!
1&
#31000000
1"
b001 %
1'
b001 *
#32000000
0"
0'
#33000000
0!
0&
#34000000
1"
1'
#35000000
0"
0'
#36000000
1!
1&
#37000000
1"
b010 %
1'
b010 *
#38000000
0"
0'
#39000000
0!
0&
#40000000
1"
1'
#41000000
0"
0'
#42000000
1!
1&
#43000000
1"
1#
b011 %
1'
1(
b011 *
#44000000
0"
0'
#45000000
0!
0&
1(
#46000000
1"
1'
#47000000
0"
0'
#48000000
1!
1&
1(
#49000000
1"
0#
1$
b100 %
1'
0(
1)
b100 *
#50000000
0"
0'
#51000000
#52000000
1"
1#
b101 %
1'
1(
1)
b101 *
#53000000
0"
0'
#54000000
0!
0&
1(
1)
#55000000
1"
1'
#56000000
0"
0'
#57000000
1!
1&
1(
1)
#58000000
1"
b110 %
1'
1(
1)
b110 *
#59000000
0"
0'
#60000000
0!
0&
1(
1)
#61000000
1"
1'
#62000000
0"
0'
#63000000
1!
1&
1(
1)
#64000000
1"
b111 %
1'
1(
1)
b111 *
#65000000
0"
0'
#66000000
0!
0&
1(
1)
#67000000
1"
1'
#68000000
0"
0'
#69000000
1!
1&
1(
1)
#70000000
1"
0#
0$
b000 %
1'
0(
0)
b000 *
