textbook/chap_8/9.vhdl
library IEEE;
use IEEE.std_logic_1164.all;

entity fsm_9 is
	port( X, CLK:    in  std_logic;
	      Z1, Z2:    out std_logic;
	      Y:	 out std_logic_vector (1 downto 0));
end fsm_9;

architecture exercise of fsm_9 is
	type state_type is (A, B, C, D);
	signal PS, NS: state_type;

begin
	sync_proc: process (CLK, NS)
	begin
		if(rising_edge(CLK)) then PS <= NS;
		end if;
	end process sync_proc;

	comb_proc: process (PS, X)
	begin
		Z1 <= '0';
		Z2 <= '0';
		case PS is
			when A =>
				Z1 <= '0';

				if(X = '0') then
					Z2 <= '0';
					NS <= A;
				else
					Z2 <= '0';
					NS <= B;
				end if;

			when B =>
				Z1 <= '0';

				if(X = '0') then
					Z2 <= '0';
					NS <= A;
				else
					Z2 <= '0';
					NS <= C;
				end if;

			when C =>
				Z1 <= '0';

				if(X = '0') then
					Z2 <= '0';
					NS <= A;
				else
					Z2 <= '0';
					NS <= D;
				end if;

			when D =>
				Z1 <= '1';

				if(X = '0') then
					Z2 <= '0';
					NS <= A;
				else
					Z2 <= '1';
					NS <= D;
				end if;

			when others =>
				Z1 <= '0';
				Z2 <= '0';
				NS <= A;
		end case;
	end process comb_proc;

	with PS select
		Y <= "00" when A,
		     "01" when B,
		     "10" when C,
		     "11" when D,
		     "00" when others;
end exercise;

textbook/chap_8/9_tb.vhdl
library IEEE;
use IEEE.std_logic_1164.all;

entity ex_9_tb is
end ex_9_tb;

architecture test of ex_9_tb is
	component fsm_9
		port
		(
			X, CLK:    in  std_logic;
	      		Z1, Z2:    out std_logic;
	      		Y:	   out std_logic_vector (1 downto 0)
		);
	end component;

	signal X, CLK, Z1, Z2: std_logic;
	signal Y: std_logic_vector (1 downto 0);

begin
	exercise: fsm_9 port map (X => X, CLK => CLK, Z1 => Z1, Z2 => Z2, Y => Y);

	process begin

--A
	X <= '0';
	CLK <= '0';
	wait for 1 ns;

	CLK <= '1';
	wait for 1 ns;

	CLK <= '0';
	wait for 1 ns;

	X <= '1';
	CLK <= '0';
	wait for 1 ns;

	CLK <= '1';
	wait for 1 ns;

	CLK <= '0';
	wait for 1 ns;

--B
	X <= '0';
	CLK <= '0';
	wait for 1 ns;

	CLK <= '1';
	wait for 1 ns;

	CLK <= '0';
	wait for 1 ns;

--A
	X <= '1';
	CLK <= '0';
	wait for 1 ns;

	CLK <= '1';
	wait for 1 ns;

	CLK <= '0';
	wait for 1 ns;

--B
	X <= '1';
	CLK <= '0';
	wait for 1 ns;

	CLK <= '1';
	wait for 1 ns;

	CLK <= '0';
	wait for 1 ns;

--C
	X <= '0';
	CLK <= '0';
	wait for 1 ns;

	CLK <= '1';
	wait for 1 ns;

	CLK <= '0';
	wait for 1 ns;

--A
	X <= '1';
	CLK <= '0';
	wait for 1 ns;

	CLK <= '1';
	wait for 1 ns;

	CLK <= '0';
	wait for 1 ns;

--B
	X <= '1';
	CLK <= '0';
	wait for 1 ns;

	CLK <= '1';
	wait for 1 ns;

	CLK <= '0';
	wait for 1 ns;

--C
	X <= '1';
	CLK <= '0';
	wait for 1 ns;

	CLK <= '1';
	wait for 1 ns;

	CLK <= '0';
	wait for 1 ns;

--C
	X <= '1';
	CLK <= '0';
	wait for 1 ns;

	CLK <= '1';
	wait for 1 ns;

	CLK <= '0';
	wait for 1 ns;

	X <= '0';
	CLK <= '0';
	wait for 1 ns;

	CLK <= '1';
	wait for 1 ns;

	CLK <= '0';
	wait for 1 ns;

	assert false report "Reached end of test";
	wait;

	end process;

end test;

textbook/chap_8/9.vcd
$date
  Tue Sep 29 21:35:47 2020
$end
$version
  GHDL v0
$end
$timescale
  1 fs
$end
$scope module standard $end
$upscope $end
$scope module std_logic_1164 $end
$upscope $end
$scope module ex_9_tb $end
$var reg 1 ! x $end
$var reg 1 " clk $end
$var reg 1 # z1 $end
$var reg 1 $ z2 $end
$var reg 2 % y[1:0] $end
$scope module exercise $end
$var reg 1 & x $end
$var reg 1 ' clk $end
$var reg 1 ( z1 $end
$var reg 1 ) z2 $end
$var reg 2 * y[1:0] $end
$comment ps is not handled $end
$comment ns is not handled $end
$upscope $end
$upscope $end
$enddefinitions $end
#0
0!
0"
0#
0$
b00 %
0&
0'
0(
0)
b00 *
#1000000
1"
1'
#2000000
0"
0'
#3000000
1!
1&
#4000000
1"
b01 %
1'
b01 *
#5000000
0"
0'
#6000000
0!
0&
#7000000
1"
b00 %
1'
b00 *
#8000000
0"
0'
#9000000
1!
1&
#10000000
1"
b01 %
1'
b01 *
#11000000
0"
0'
#12000000
#13000000
1"
b10 %
1'
b10 *
#14000000
0"
0'
#15000000
0!
0&
#16000000
1"
b00 %
1'
b00 *
#17000000
0"
0'
#18000000
1!
1&
#19000000
1"
b01 %
1'
b01 *
#20000000
0"
0'
#21000000
#22000000
1"
b10 %
1'
b10 *
#23000000
0"
0'
#24000000
#25000000
1"
1#
1$
b11 %
1'
1(
1)
b11 *
#26000000
0"
0'
#27000000
#28000000
1"
1'
#29000000
0"
0'
#30000000
0!
0$
0&
1(
0)
#31000000
1"
0#
b00 %
1'
0(
b00 *
