textbook/chap_4/2a.vhdl
library IEEE;
use IEEE.std_logic_1164.all;

entity ex_2a is
	port(	A, B, C, D: 	in	std_logic;
		F:		out	std_logic_vector (0 downto 0));
end ex_2a;

architecture exercise of ex_2a is
	signal A1: std_logic_vector (3 downto 0);
begin
	A1 <= (A & B & C & D);
	with A1 select
		F <= "1" when "0010"|"0011"|"0110"|"1010"|"1011"|"1110",
		     "0" when others;
end exercise;

textbook/chap_4/2a_tb.vhdl
library IEEE;
use IEEE.std_logic_1164.all;

entity ex_2a_tb is
end ex_2a_tb;

architecture test of ex_2a_tb is
	component ex_2a
		port
		(
			A, B, C, D:	in	std_logic;
			F:		out	std_logic_vector (0 downto 0)
		);
	end component;

	signal A, B, C, D: std_logic;
	signal F:	   std_logic_vector (0 downto 0);

begin
	exercise: ex_2a port map (A => A, B => B, C => C, D => D, F => F);

	process begin

	A <= 'X';
	B <= 'X';
	C <= 'X';
	D <= 'X';
	wait for 1 ns;

	A <= '1';
	B <= '1';
	C <= '1';
	D <= '1';
	wait for 1 ns;

	A <= '1';
	B <= '1';
	C <= '1';
	D <= '0';
	wait for 1 ns;

	A <= '1';
	B <= '1';
	C <= '0';
	D <= '1';
	wait for 1 ns;

	A <= '1';
	B <= '1';
	C <= '0';
	D <= '0';
	wait for 1 ns;

	A <= '1';
	B <= '0';
	C <= '1';
	D <= '1';
	wait for 1 ns;

	A <= '1';
	B <= '0';
	C <= '1';
	D <= '0';
	wait for 1 ns;

	A <= '1';
	B <= '0';
	C <= '0';
	D <= '1';
	wait for 1 ns;

	A <= '1';
	B <= '0';
	C <= '0';
	D <= '0';
	wait for 1 ns;

	A <= '0';
	B <= '1';
	C <= '1';
	D <= '1';
	wait for 1 ns;

	A <= '0';
	B <= '1';
	C <= '1';
	D <= '0';
	wait for 1 ns;

	A <= '0';
	B <= '1';
	C <= '0';
	D <= '1';
	wait for 1 ns;

	A <= '0';
	B <= '1';
	C <= '0';
	D <= '0';
	wait for 1 ns;

	A <= '0';
	B <= '0';
	C <= '1';
	D <= '1';
	wait for 1 ns;

	A <= '0';
	B <= '0';
	C <= '1';
	D <= '0';
	wait for 1 ns;

	A <= '0';
	B <= '0';
	C <= '0';
	D <= '1';
	wait for 1 ns;

	A <= '0';
	B <= '0';
	C <= '0';
	D <= '0';
	wait for 1 ns;

	assert false report "Reached end of test";
	wait;

	end process;

end test;

textbook/chap_4/2a.vcd
$date
  Sun Sep 20 21:22:11 2020
$end
$version
  GHDL v0
$end
$timescale
  1 fs
$end
$scope module standard $end
$upscope $end
$scope module std_logic_1164 $end
$upscope $end
$scope module ex_2a_tb $end
$var reg 1 ! a $end
$var reg 1 " b $end
$var reg 1 # c $end
$var reg 1 $ d $end
$var reg 1 % f[0:0] $end
$scope module exercise $end
$var reg 1 & a $end
$var reg 1 ' b $end
$var reg 1 ( c $end
$var reg 1 ) d $end
$var reg 1 * f[0:0] $end
$var reg 4 + a1[3:0] $end
$upscope $end
$upscope $end
$enddefinitions $end
#0
X!
X"
X#
X$
b0 %
X&
X'
X(
X)
b0 *
bXXXX +
#1000000
1!
1"
1#
1$
1&
1'
1(
1)
b1111 +
#2000000
0$
b1 %
0)
b1 *
b1110 +
#3000000
0#
1$
b0 %
0(
1)
b0 *
b1101 +
#4000000
0$
0)
b1100 +
#5000000
0"
1#
1$
b1 %
0'
1(
1)
b1 *
b1011 +
#6000000
0$
0)
b1010 +
#7000000
0#
1$
b0 %
0(
1)
b0 *
b1001 +
#8000000
0$
0)
b1000 +
#9000000
0!
1"
1#
1$
0&
1'
1(
1)
b0111 +
#10000000
0$
b1 %
0)
b1 *
b0110 +
#11000000
0#
1$
b0 %
0(
1)
b0 *
b0101 +
#12000000
0$
0)
b0100 +
#13000000
0"
1#
1$
b1 %
0'
1(
1)
b1 *
b0011 +
#14000000
0$
0)
b0010 +
#15000000
0#
1$
b0 %
0(
1)
b0 *
b0001 +
#16000000
0$
0)
b0000 +
