textbook/chap_4/2c.vhdl
library IEEE;
use IEEE.std_logic_1164.all;

entity ex_2c is
	port(	A, B, C, D: 	in	std_logic;
		F:		out	std_logic);
end ex_2c;

architecture exercise of ex_2c is
begin
	F <= '0' when (A = '0' and B = '0' and C = '1' and D = '0') else
	     '0' when (A = '0' and B = '0' and C = '1' and D = '1') else
	     '1';
end exercise;

textbook/chap_4/2c_tb.vhdl
library IEEE;
use IEEE.std_logic_1164.all;

entity ex_2c_tb is
end ex_2c_tb;

architecture test of ex_2c_tb is
	component ex_2c
		port
		(
			A, B, C, D:	in	std_logic;
			F:		out	std_logic
		);
	end component;

	signal A, B, C, D, F: std_logic;

begin
	exercise: ex_2c port map (A => A, B => B, C => C, D => D, F => F);

	process begin

	A <= 'X';
	B <= 'X';
	C <= 'X';
	D <= 'X';
	wait for 1 ns;

	A <= '1';
	B <= '1';
	C <= '1';
	D <= '1';
	wait for 1 ns;

	A <= '1';
	B <= '1';
	C <= '1';
	D <= '0';
	wait for 1 ns;

	A <= '1';
	B <= '1';
	C <= '0';
	D <= '1';
	wait for 1 ns;

	A <= '1';
	B <= '1';
	C <= '0';
	D <= '0';
	wait for 1 ns;

	A <= '1';
	B <= '0';
	C <= '1';
	D <= '1';
	wait for 1 ns;

	A <= '1';
	B <= '0';
	C <= '1';
	D <= '0';
	wait for 1 ns;

	A <= '1';
	B <= '0';
	C <= '0';
	D <= '1';
	wait for 1 ns;

	A <= '1';
	B <= '0';
	C <= '0';
	D <= '0';
	wait for 1 ns;

	A <= '0';
	B <= '1';
	C <= '1';
	D <= '1';
	wait for 1 ns;

	A <= '0';
	B <= '1';
	C <= '1';
	D <= '0';
	wait for 1 ns;

	A <= '0';
	B <= '1';
	C <= '0';
	D <= '1';
	wait for 1 ns;

	A <= '0';
	B <= '1';
	C <= '0';
	D <= '0';
	wait for 1 ns;

	A <= '0';
	B <= '0';
	C <= '1';
	D <= '1';
	wait for 1 ns;

	A <= '0';
	B <= '0';
	C <= '1';
	D <= '0';
	wait for 1 ns;

	A <= '0';
	B <= '0';
	C <= '0';
	D <= '1';
	wait for 1 ns;

	A <= '0';
	B <= '0';
	C <= '0';
	D <= '0';
	wait for 1 ns;

	assert false report "Reached end of test";
	wait;

	end process;

end test;

textbook/chap_4/2c.vcd
$date
  Sun Sep 20 22:09:03 2020
$end
$version
  GHDL v0
$end
$timescale
  1 fs
$end
$scope module standard $end
$upscope $end
$scope module std_logic_1164 $end
$upscope $end
$scope module ex_2c_tb $end
$var reg 1 ! a $end
$var reg 1 " b $end
$var reg 1 # c $end
$var reg 1 $ d $end
$var reg 1 % f $end
$scope module exercise $end
$var reg 1 & a $end
$var reg 1 ' b $end
$var reg 1 ( c $end
$var reg 1 ) d $end
$var reg 1 * f $end
$upscope $end
$upscope $end
$enddefinitions $end
#0
X!
X"
X#
X$
1%
X&
X'
X(
X)
1*
#1000000
1!
1"
1#
1$
1&
1'
1(
1)
#2000000
0$
0)
#3000000
0#
1$
0(
1)
#4000000
0$
0)
#5000000
0"
1#
1$
0'
1(
1)
#6000000
0$
0)
#7000000
0#
1$
0(
1)
#8000000
0$
0)
#9000000
0!
1"
1#
1$
0&
1'
1(
1)
#10000000
0$
0)
#11000000
0#
1$
0(
1)
#12000000
0$
0)
#13000000
0"
1#
1$
0%
0'
1(
1)
0*
#14000000
0$
0)
#15000000
0#
1$
1%
0(
1)
1*
#16000000
0$
0)
