textbook/chap_4/4.vhdl
library IEEE;
use IEEE.std_logic_1164.all;

entity ex_4 is
	port(	input: 	in	std_logic_vector (7 downto 0);
		F:	out	std_logic_vector (0 downto 0));
end ex_4;

architecture exercise of ex_4 is
begin
	with (input) select
	F <= "0" when "00000000",
	     "1" when others;
end exercise;

textbook/chap_4/4_tb.vhdl
library IEEE;
use IEEE.std_logic_1164.all;

entity ex_4_tb is
end ex_4_tb;

architecture test of ex_4_tb is
	component ex_4		port
		(
			input:	in	std_logic_vector (7 downto 0);
			F:	out	std_logic_vector (0 downto 0)
		);
	end component;

	signal input: std_logic_vector (7 downto 0);
	signal F:     std_logic_vector (0 downto 0);

	type range_a is range 0 to 1;
	type range_b is range 0 to 1;
	type range_c is range 0 to 1;
	type range_d is range 0 to 1;
	type range_e is range 0 to 1;
	type range_g is range 0 to 1;
	type range_h is range 0 to 1;
	type range_i is range 0 to 1;

begin
	exercise: ex_4 port map (input => input, F => F);

	process begin

		for a in range_a loop
			if a = 0 then
				input(0) <= '0';
			else
				input(0) <= '1';
			end if;

			for b in range_b loop
				if b = 0 then
					input(1) <= '0';
				else
					input(1) <= '1';
				end if;

				for c in range_c loop
					if c = 0 then
						input(2) <= '0';
					else
						input(2) <= '1';
					end if;

					for d in range_d loop
						if d = 0 then
							input(3) <= '0';
						else
							input(3) <= '1';
						end if;

						for e in range_e loop
							if e = 0 then
								input(4) <= '0';
							else
								input(4) <= '1';
							end if;

							for g in range_g loop
								if g = 0 then
									input(5) <= '0';
								else
									input(5) <= '1';
								end if;

								for h in range_h loop
									if h = 0 then
										input(6) <= '0';
									else
										input(6) <= '1';
									end if;

									for i in range_i loop
										if i = 0 then
											input(7) <= '0';
										else
											input(7) <= '1';
										end if;
										wait for 1 ns;
									end loop;
								end loop;
							end loop;
						end loop;
					end loop;
				end loop;
			end loop;
		end loop;
        report "1" severity error;
wait;

	end process;
		

end test;

textbook/chap_4/4.vcd
$date
  Sun Sep 20 23:45:13 2020
$end
$version
  GHDL v0
$end
$timescale
  1 fs
$end
$scope module standard $end
$upscope $end
$scope module std_logic_1164 $end
$upscope $end
$scope module ex_4_tb $end
$var reg 8 ! input[7:0] $end
$var reg 1 " f[0:0] $end
$scope module exercise $end
$var reg 8 # input[7:0] $end
$var reg 1 $ f[0:0] $end
$upscope $end
$upscope $end
$enddefinitions $end
#0
b00000000 !
b0 "
b00000000 #
b0 $
#1000000
b10000000 !
b1 "
b10000000 #
b1 $
#2000000
b01000000 !
b01000000 #
#3000000
b11000000 !
b11000000 #
#4000000
b00100000 !
b00100000 #
#5000000
b10100000 !
b10100000 #
#6000000
b01100000 !
b01100000 #
#7000000
b11100000 !
b11100000 #
#8000000
b00010000 !
b00010000 #
#9000000
b10010000 !
b10010000 #
#10000000
b01010000 !
b01010000 #
#11000000
b11010000 !
b11010000 #
#12000000
b00110000 !
b00110000 #
#13000000
b10110000 !
b10110000 #
#14000000
b01110000 !
b01110000 #
#15000000
b11110000 !
b11110000 #
#16000000
b00001000 !
b00001000 #
#17000000
b10001000 !
b10001000 #
#18000000
b01001000 !
b01001000 #
#19000000
b11001000 !
b11001000 #
#20000000
b00101000 !
b00101000 #
#21000000
b10101000 !
b10101000 #
#22000000
b01101000 !
b01101000 #
#23000000
b11101000 !
b11101000 #
#24000000
b00011000 !
b00011000 #
#25000000
b10011000 !
b10011000 #
#26000000
b01011000 !
b01011000 #
#27000000
b11011000 !
b11011000 #
#28000000
b00111000 !
b00111000 #
#29000000
b10111000 !
b10111000 #
#30000000
b01111000 !
b01111000 #
#31000000
b11111000 !
b11111000 #
#32000000
b00000100 !
b00000100 #
#33000000
b10000100 !
b10000100 #
#34000000
b01000100 !
b01000100 #
#35000000
b11000100 !
b11000100 #
#36000000
b00100100 !
b00100100 #
#37000000
b10100100 !
b10100100 #
#38000000
b01100100 !
b01100100 #
#39000000
b11100100 !
b11100100 #
#40000000
b00010100 !
b00010100 #
#41000000
b10010100 !
b10010100 #
#42000000
b01010100 !
b01010100 #
#43000000
b11010100 !
b11010100 #
#44000000
b00110100 !
b00110100 #
#45000000
b10110100 !
b10110100 #
#46000000
b01110100 !
b01110100 #
#47000000
b11110100 !
b11110100 #
#48000000
b00001100 !
b00001100 #
#49000000
b10001100 !
b10001100 #
#50000000
b01001100 !
b01001100 #
#51000000
b11001100 !
b11001100 #
#52000000
b00101100 !
b00101100 #
#53000000
b10101100 !
b10101100 #
#54000000
b01101100 !
b01101100 #
#55000000
b11101100 !
b11101100 #
#56000000
b00011100 !
b00011100 #
#57000000
b10011100 !
b10011100 #
#58000000
b01011100 !
b01011100 #
#59000000
b11011100 !
b11011100 #
#60000000
b00111100 !
b00111100 #
#61000000
b10111100 !
b10111100 #
#62000000
b01111100 !
b01111100 #
#63000000
b11111100 !
b11111100 #
#64000000
b00000010 !
b00000010 #
#65000000
b10000010 !
b10000010 #
#66000000
b01000010 !
b01000010 #
#67000000
b11000010 !
b11000010 #
#68000000
b00100010 !
b00100010 #
#69000000
b10100010 !
b10100010 #
#70000000
b01100010 !
b01100010 #
#71000000
b11100010 !
b11100010 #
#72000000
b00010010 !
b00010010 #
#73000000
b10010010 !
b10010010 #
#74000000
b01010010 !
b01010010 #
#75000000
b11010010 !
b11010010 #
#76000000
b00110010 !
b00110010 #
#77000000
b10110010 !
b10110010 #
#78000000
b01110010 !
b01110010 #
#79000000
b11110010 !
b11110010 #
#80000000
b00001010 !
b00001010 #
#81000000
b10001010 !
b10001010 #
#82000000
b01001010 !
b01001010 #
#83000000
b11001010 !
b11001010 #
#84000000
b00101010 !
b00101010 #
#85000000
b10101010 !
b10101010 #
#86000000
b01101010 !
b01101010 #
#87000000
b11101010 !
b11101010 #
#88000000
b00011010 !
b00011010 #
#89000000
b10011010 !
b10011010 #
#90000000
b01011010 !
b01011010 #
#91000000
b11011010 !
b11011010 #
#92000000
b00111010 !
b00111010 #
#93000000
b10111010 !
b10111010 #
#94000000
b01111010 !
b01111010 #
#95000000
b11111010 !
b11111010 #
#96000000
b00000110 !
b00000110 #
#97000000
b10000110 !
b10000110 #
#98000000
b01000110 !
b01000110 #
#99000000
b11000110 !
b11000110 #
#100000000
b00100110 !
b00100110 #
#101000000
b10100110 !
b10100110 #
#102000000
b01100110 !
b01100110 #
#103000000
b11100110 !
b11100110 #
#104000000
b00010110 !
b00010110 #
#105000000
b10010110 !
b10010110 #
#106000000
b01010110 !
b01010110 #
#107000000
b11010110 !
b11010110 #
#108000000
b00110110 !
b00110110 #
#109000000
b10110110 !
b10110110 #
#110000000
b01110110 !
b01110110 #
#111000000
b11110110 !
b11110110 #
#112000000
b00001110 !
b00001110 #
#113000000
b10001110 !
b10001110 #
#114000000
b01001110 !
b01001110 #
#115000000
b11001110 !
b11001110 #
#116000000
b00101110 !
b00101110 #
#117000000
b10101110 !
b10101110 #
#118000000
b01101110 !
b01101110 #
#119000000
b11101110 !
b11101110 #
#120000000
b00011110 !
b00011110 #
#121000000
b10011110 !
b10011110 #
#122000000
b01011110 !
b01011110 #
#123000000
b11011110 !
b11011110 #
#124000000
b00111110 !
b00111110 #
#125000000
b10111110 !
b10111110 #
#126000000
b01111110 !
b01111110 #
#127000000
b11111110 !
b11111110 #
#128000000
b00000001 !
b00000001 #
#129000000
b10000001 !
b10000001 #
#130000000
b01000001 !
b01000001 #
#131000000
b11000001 !
b11000001 #
#132000000
b00100001 !
b00100001 #
#133000000
b10100001 !
b10100001 #
#134000000
b01100001 !
b01100001 #
#135000000
b11100001 !
b11100001 #
#136000000
b00010001 !
b00010001 #
#137000000
b10010001 !
b10010001 #
#138000000
b01010001 !
b01010001 #
#139000000
b11010001 !
b11010001 #
#140000000
b00110001 !
b00110001 #
#141000000
b10110001 !
b10110001 #
#142000000
b01110001 !
b01110001 #
#143000000
b11110001 !
b11110001 #
#144000000
b00001001 !
b00001001 #
#145000000
b10001001 !
b10001001 #
#146000000
b01001001 !
b01001001 #
#147000000
b11001001 !
b11001001 #
#148000000
b00101001 !
b00101001 #
#149000000
b10101001 !
b10101001 #
#150000000
b01101001 !
b01101001 #
#151000000
b11101001 !
b11101001 #
#152000000
b00011001 !
b00011001 #
#153000000
b10011001 !
b10011001 #
#154000000
b01011001 !
b01011001 #
#155000000
b11011001 !
b11011001 #
#156000000
b00111001 !
b00111001 #
#157000000
b10111001 !
b10111001 #
#158000000
b01111001 !
b01111001 #
#159000000
b11111001 !
b11111001 #
#160000000
b00000101 !
b00000101 #
#161000000
b10000101 !
b10000101 #
#162000000
b01000101 !
b01000101 #
#163000000
b11000101 !
b11000101 #
#164000000
b00100101 !
b00100101 #
#165000000
b10100101 !
b10100101 #
#166000000
b01100101 !
b01100101 #
#167000000
b11100101 !
b11100101 #
#168000000
b00010101 !
b00010101 #
#169000000
b10010101 !
b10010101 #
#170000000
b01010101 !
b01010101 #
#171000000
b11010101 !
b11010101 #
#172000000
b00110101 !
b00110101 #
#173000000
b10110101 !
b10110101 #
#174000000
b01110101 !
b01110101 #
#175000000
b11110101 !
b11110101 #
#176000000
b00001101 !
b00001101 #
#177000000
b10001101 !
b10001101 #
#178000000
b01001101 !
b01001101 #
#179000000
b11001101 !
b11001101 #
#180000000
b00101101 !
b00101101 #
#181000000
b10101101 !
b10101101 #
#182000000
b01101101 !
b01101101 #
#183000000
b11101101 !
b11101101 #
#184000000
b00011101 !
b00011101 #
#185000000
b10011101 !
b10011101 #
#186000000
b01011101 !
b01011101 #
#187000000
b11011101 !
b11011101 #
#188000000
b00111101 !
b00111101 #
#189000000
b10111101 !
b10111101 #
#190000000
b01111101 !
b01111101 #
#191000000
b11111101 !
b11111101 #
#192000000
b00000011 !
b00000011 #
#193000000
b10000011 !
b10000011 #
#194000000
b01000011 !
b01000011 #
#195000000
b11000011 !
b11000011 #
#196000000
b00100011 !
b00100011 #
#197000000
b10100011 !
b10100011 #
#198000000
b01100011 !
b01100011 #
#199000000
b11100011 !
b11100011 #
#200000000
b00010011 !
b00010011 #
#201000000
b10010011 !
b10010011 #
#202000000
b01010011 !
b01010011 #
#203000000
b11010011 !
b11010011 #
#204000000
b00110011 !
b00110011 #
#205000000
b10110011 !
b10110011 #
#206000000
b01110011 !
b01110011 #
#207000000
b11110011 !
b11110011 #
#208000000
b00001011 !
b00001011 #
#209000000
b10001011 !
b10001011 #
#210000000
b01001011 !
b01001011 #
#211000000
b11001011 !
b11001011 #
#212000000
b00101011 !
b00101011 #
#213000000
b10101011 !
b10101011 #
#214000000
b01101011 !
b01101011 #
#215000000
b11101011 !
b11101011 #
#216000000
b00011011 !
b00011011 #
#217000000
b10011011 !
b10011011 #
#218000000
b01011011 !
b01011011 #
#219000000
b11011011 !
b11011011 #
#220000000
b00111011 !
b00111011 #
#221000000
b10111011 !
b10111011 #
#222000000
b01111011 !
b01111011 #
#223000000
b11111011 !
b11111011 #
#224000000
b00000111 !
b00000111 #
#225000000
b10000111 !
b10000111 #
#226000000
b01000111 !
b01000111 #
#227000000
b11000111 !
b11000111 #
#228000000
b00100111 !
b00100111 #
#229000000
b10100111 !
b10100111 #
#230000000
b01100111 !
b01100111 #
#231000000
b11100111 !
b11100111 #
#232000000
b00010111 !
b00010111 #
#233000000
b10010111 !
b10010111 #
#234000000
b01010111 !
b01010111 #
#235000000
b11010111 !
b11010111 #
#236000000
b00110111 !
b00110111 #
#237000000
b10110111 !
b10110111 #
#238000000
b01110111 !
b01110111 #
#239000000
b11110111 !
b11110111 #
#240000000
b00001111 !
b00001111 #
#241000000
b10001111 !
b10001111 #
#242000000
b01001111 !
b01001111 #
#243000000
b11001111 !
b11001111 #
#244000000
b00101111 !
b00101111 #
#245000000
b10101111 !
b10101111 #
#246000000
b01101111 !
b01101111 #
#247000000
b11101111 !
b11101111 #
#248000000
b00011111 !
b00011111 #
#249000000
b10011111 !
b10011111 #
#250000000
b01011111 !
b01011111 #
#251000000
b11011111 !
b11011111 #
#252000000
b00111111 !
b00111111 #
#253000000
b10111111 !
b10111111 #
#254000000
b01111111 !
b01111111 #
#255000000
b11111111 !
b11111111 #
