textbook/chap_7/2.vhdl
library IEEE;
use IEEE.std_logic_1164.all;

entity ex_2 is
	port(	S, D, CLK, R: 	in	std_logic;
		Q, Q_N:		out	std_logic);
end ex_2;

architecture exercise of ex_2 is
	signal SR: std_logic_vector (1 downto 0);
begin
	SR <= S & R;

	my_proc: process (SR, CLK)
	begin
		case (SR) is
			when "00"   => Q <= '1';
				       Q_N <= '0';
			when "10"   => Q <= '0';
				       Q_N <= '1';
			when "01"   => Q <= '1';
				       Q_N <= '0';
			when "11"   =>
				if(rising_edge(CLK)) then
					Q <= D;
				        Q_N <= NOT(D);
				end if;
			when others => Q <= '0';
				       Q_N <= '1';
		end case;
	end process my_proc;
end exercise;

-- S=0, R=0 never happens
-- S=1, R=0 Q <= 0
-- S=0, R=1 Q <= 1
-- S=1, R=1 Q <= [depends on rising edge]

textbook/chap_7/2_tb.vhdl
library IEEE;
use IEEE.std_logic_1164.all;

entity ex_2_tb is
end ex_2_tb;

architecture test of ex_2_tb is
	component ex_2
		port
		(
			S, D, CLK, R: 	in	std_logic;
			Q, Q_N:		out	std_logic
		);
	end component;

	signal S, D, CLK, R, Q, Q_N: std_logic;

begin
	exercise: ex_2 port map (S => S, D => D, CLK => CLK, R => R, Q => Q, Q_N => Q_N);

	process begin

	S <= 'X';
	R <= 'X';
	D <= 'X';
	CLK <= '0';
	wait for 1 ns;

	S <= '0';
	R <= '0';
	D <= '0';
	CLK <= '0';
	wait for 0.5 ns;

	CLK <= '1';
	wait for 0.5 ns;

	CLK <= '0';
	wait for 0.5 ns;

	S <= '0';
	R <= '0';
	D <= '1';
	CLK <= '0';
	wait for 0.5 ns;

	CLK <= '1';
	wait for 0.5 ns;

	CLK <= '0';
	wait for 0.5 ns;

	S <= '1';
	R <= '0';
	D <= '0';
	CLK <= '0';
	wait for 0.5 ns;

	CLK <= '1';
	wait for 0.5 ns;

	CLK <= '0';
	wait for 0.5 ns;

	S <= '1';
	R <= '0';
	D <= '1';
	CLK <= '0';
	wait for 0.5 ns;

	CLK <= '1';
	wait for 0.5 ns;

	CLK <= '0';
	wait for 0.5 ns;

	S <= '0';
	R <= '1';
	D <= '0';
	CLK <= '0';
	wait for 0.5 ns;

	CLK <= '1';
	wait for 0.5 ns;

	CLK <= '0';
	wait for 0.5 ns;

	S <= '0';
	R <= '1';
	D <= '1';
	CLK <= '0';
	wait for 0.5 ns;

	CLK <= '1';
	wait for 0.5 ns;

	CLK <= '0';
	wait for 0.5 ns;

	S <= '1';
	R <= '1';
	D <= '0';
	CLK <= '0';
	wait for 0.5 ns;

	CLK <= '1';
	wait for 0.5 ns;

	CLK <= '0';
	wait for 0.5 ns;

	S <= '1';
	R <= '1';
	D <= '1';
	CLK <= '0';
	wait for 0.5 ns;

	CLK <= '1';
	wait for 0.5 ns;

	CLK <= '0';
	wait for 0.5 ns;

	assert false report "Reached end of test";
	wait;

	end process;

end test;

textbook/chap_7/2.vcd
$date
  Mon Sep 28 22:58:57 2020
$end
$version
  GHDL v0
$end
$timescale
  1 fs
$end
$scope module standard $end
$upscope $end
$scope module std_logic_1164 $end
$upscope $end
$scope module ex_2_tb $end
$var reg 1 ! s $end
$var reg 1 " d $end
$var reg 1 # clk $end
$var reg 1 $ r $end
$var reg 1 % q $end
$var reg 1 & q_n $end
$scope module exercise $end
$var reg 1 ' s $end
$var reg 1 ( d $end
$var reg 1 ) clk $end
$var reg 1 * r $end
$var reg 1 + q $end
$var reg 1 , q_n $end
$var reg 2 - sr[1:0] $end
$upscope $end
$upscope $end
$enddefinitions $end
#0
X!
X"
0#
X$
0%
1&
X'
X(
0)
X*
0+
1,
bXX -
#1000000
0!
0"
0$
1%
0&
0'
0(
0*
1+
0,
b00 -
#1500000
1#
1)
#2000000
0#
0)
#2500000
1"
1(
#3000000
1#
1)
#3500000
0#
0)
#4000000
1!
0"
0%
1&
1'
0(
0+
1,
b10 -
#4500000
1#
1)
#5000000
0#
0)
#5500000
1"
1(
#6000000
1#
1)
#6500000
0#
0)
#7000000
0!
0"
1$
1%
0&
0'
0(
1*
1+
0,
b01 -
#7500000
1#
1)
#8000000
0#
0)
#8500000
1"
1(
#9000000
1#
1)
#9500000
0#
0)
#10000000
1!
0"
1'
0(
b11 -
#10500000
1#
0%
1&
1)
0+
1,
#11000000
0#
0)
#11500000
1"
1(
#12000000
1#
1%
0&
1)
1+
0,
