textbook/chap_7/5_eq.vhdl
library IEEE;
use IEEE.std_logic_1164.all;

entity ex_5_eq is
	port(	S, T, CLK, R: 	in	std_logic;
		Q, Q_N:		out	std_logic);
end ex_5_eq;

architecture exercise of ex_5_eq is
	signal SR: std_logic_vector (1 downto 0);
	signal LSR: std_logic_vector (1 downto 0);
	signal temp:  std_logic;
begin
	SR <= S & R;

	my_proc: process (SR, CLK)
	begin
		case (SR) is
			when "00"   => temp <= '0';
			when "10"   => temp <= '0';
			when "01"   => temp <= '1';
			when "11"   =>
				if(rising_edge(CLK)) then
					temp <= T XOR temp;
				end if;
			when others => temp <= '0';
		end case;

		LSR <= SR;
	end process my_proc;
	Q <= temp;
	Q_N <= NOT(temp);
end exercise;

textbook/chap_7/5_eq_tb.vhdl
library IEEE;
use IEEE.std_logic_1164.all;

entity ex_5_eq_tb is
end ex_5_eq_tb;

architecture test of ex_5_eq_tb is
	component ex_5_eq
		port
		(
			S, T, CLK, R: 	in	std_logic;
			Q, Q_N:		out	std_logic
		);
	end component;

	signal S, D, CLK, R, Q, Q_N: std_logic;

begin
	exercise: ex_5_eq port map (S => S, T => D, CLK => CLK, R => R, Q => Q, Q_N => Q_N);

	process begin

	S <= 'X';
	R <= 'X';
	D <= 'X';
	CLK <= '0';
	wait for 1 ns;


	S <= '1';
	R <= '0';
	D <= '0';
	CLK <= '0';
	wait for 0.5 ns;

	CLK <= '1';
	wait for 0.5 ns;

	CLK <= '0';
	wait for 0.5 ns;

	S <= '1';
	R <= '0';
	D <= '1';
	CLK <= '0';
	wait for 0.5 ns;

	CLK <= '1';
	wait for 0.5 ns;

	CLK <= '0';
	wait for 0.5 ns;

	S <= '0';
	R <= '1';
	D <= '0';
	CLK <= '0';
	wait for 0.5 ns;

	CLK <= '1';
	wait for 0.5 ns;

	CLK <= '0';
	wait for 0.5 ns;

	S <= '0';
	R <= '1';
	D <= '1';
	CLK <= '0';
	wait for 0.5 ns;

	CLK <= '1';
	wait for 0.5 ns;

	CLK <= '0';
	wait for 0.5 ns;

	S <= '1';
	R <= '1';
	D <= '0';
	CLK <= '0';
	wait for 0.5 ns;

	CLK <= '1';
	wait for 0.5 ns;

	CLK <= '0';
	wait for 0.5 ns;

	S <= '1';
	R <= '1';
	D <= '1';
	CLK <= '0';
	wait for 0.5 ns;

	CLK <= '1';
	wait for 0.5 ns;

	CLK <= '0';
	wait for 0.5 ns;

	S <= '1';
	R <= '1';
	D <= '1';
	CLK <= '0';
	wait for 0.5 ns;

	CLK <= '1';
	wait for 0.5 ns;

	CLK <= '0';
	wait for 0.5 ns;

	S <= '1';
	R <= '1';
	D <= '1';
	CLK <= '0';
	wait for 0.5 ns;

	CLK <= '1';
	wait for 0.5 ns;

	CLK <= '0';
	wait for 0.5 ns;

	S <= '1';
	R <= '1';
	D <= '0';
	CLK <= '0';
	wait for 0.5 ns;

	CLK <= '1';
	wait for 0.5 ns;

	CLK <= '0';
	wait for 0.5 ns;

	assert false report "Reached end of test";
	wait;

	end process;

end test;

textbook/chap_7/5_eq.vcd
$date
  Tue Sep 29 12:54:34 2020
$end
$version
  GHDL v0
$end
$timescale
  1 fs
$end
$scope module standard $end
$upscope $end
$scope module std_logic_1164 $end
$upscope $end
$scope module ex_5_eq_tb $end
$var reg 1 ! s $end
$var reg 1 " d $end
$var reg 1 # clk $end
$var reg 1 $ r $end
$var reg 1 % q $end
$var reg 1 & q_n $end
$scope module exercise $end
$var reg 1 ' s $end
$var reg 1 ( t $end
$var reg 1 ) clk $end
$var reg 1 * r $end
$var reg 1 + q $end
$var reg 1 , q_n $end
$var reg 2 - sr[1:0] $end
$var reg 2 . lsr[1:0] $end
$var reg 1 / temp $end
$upscope $end
$upscope $end
$enddefinitions $end
#0
X!
X"
0#
X$
0%
1&
X'
X(
0)
X*
0+
1,
bXX -
bXX .
0/
#1000000
1!
0"
0$
1'
0(
0*
b10 -
b10 .
#1500000
1#
1)
#2000000
0#
0)
#2500000
1"
1(
#3000000
1#
1)
#3500000
0#
0)
#4000000
0!
0"
1$
1%
0&
0'
0(
1*
1+
0,
b01 -
b01 .
1/
#4500000
1#
1)
#5000000
0#
0)
#5500000
1"
1(
#6000000
1#
1)
#6500000
0#
0)
#7000000
1!
0"
1'
0(
b11 -
b11 .
#7500000
1#
1)
#8000000
0#
0)
#8500000
1"
1(
#9000000
1#
0%
1&
1)
0+
1,
0/
#9500000
0#
0)
#10000000
#10500000
1#
1%
0&
1)
1+
0,
1/
#11000000
0#
0)
#11500000
#12000000
1#
0%
1&
1)
0+
1,
0/
#12500000
0#
0)
#13000000
0"
0(
