textbook/chap_5/1b_case.vhdl
library IEEE;
use IEEE.std_logic_1164.all;

entity ex_1b_case is
	port(	A, B, C, D: 	in	std_logic;
		F:		out	std_logic);
end ex_1b_case;

architecture exercise of ex_1b_case is
	signal ABCD: std_logic_vector (3 downto 0);
begin
	ABCD <= A & B & C & D;

	my_proc: process (ABCD)
	begin
		case (ABCD) is
			when "1110"   => F <= '1';
			when "1011"   => F <= '1';
			when "1010"   => F <= '1';
			when "0110"   => F <= '1';
			when "0011"   => F <= '1';
			when "0010"   => F <= '1';
			when others => F <= '0';
		end case;
	end process my_proc;
end exercise;

--A'CD' + B'C + BCD'
--A	B	C	D	A'CD'	B'C	BCD'	F
--1	1	1	1	0	0	0	0
--*1	1	1	0	0	0	1	1
--1	1	0	1	0	0	0	0
--1	1	0	0	0	0	0	0
--*1	0	1	1	0	1	0	1
--*1	0	1	0	0	1	0	1
--1	0	0	1	0	0	0	0
--1	0	0	0	0	0	0	0
--0	1	1	1	0	0	0	0
--*0	1	1	0	1	0	1	1
--0	1	0	1	0	0	0	0
--0	1	0	0	0	0	0	0
--*0	0	1	1	0	1	0	1
--*0	0	1	0	1	1	0	1
--0	0	0	1	0	0	0	0
--0	0	0	0	0	0	0	0

--True for: 1110 1011 1010 0110 0011 0010

textbook/chap_5/1b_case_tb.vhdl
library IEEE;
use IEEE.std_logic_1164.all;

entity ex_1b_case_tb is
end ex_1b_case_tb;

architecture test of ex_1b_case_tb is
	component ex_1b_case
		port
		(
			A, B, C, D:	in	std_logic;
			F:		out	std_logic
		);
	end component;

	signal A, B, C, D, F: std_logic;

begin
	exercise: ex_1b_case port map (A => A, B => B, C => C, D => D, F => F);

	process begin

	A <= 'X';
	B <= 'X';
	C <= 'X';
	D <= 'X';
	wait for 1 ns;

	A <= '1';
	B <= '1';
	C <= '1';
	D <= '1';
	wait for 1 ns;

	A <= '1';
	B <= '1';
	C <= '1';
	D <= '0';
	wait for 1 ns;

	A <= '1';
	B <= '1';
	C <= '0';
	D <= '1';
	wait for 1 ns;

	A <= '1';
	B <= '1';
	C <= '0';
	D <= '0';
	wait for 1 ns;

	A <= '1';
	B <= '0';
	C <= '1';
	D <= '1';
	wait for 1 ns;

	A <= '1';
	B <= '0';
	C <= '1';
	D <= '0';
	wait for 1 ns;

	A <= '1';
	B <= '0';
	C <= '0';
	D <= '1';
	wait for 1 ns;

	A <= '1';
	B <= '0';
	C <= '0';
	D <= '0';
	wait for 1 ns;

	A <= '0';
	B <= '1';
	C <= '1';
	D <= '1';
	wait for 1 ns;

	A <= '0';
	B <= '1';
	C <= '1';
	D <= '0';
	wait for 1 ns;

	A <= '0';
	B <= '1';
	C <= '0';
	D <= '1';
	wait for 1 ns;

	A <= '0';
	B <= '1';
	C <= '0';
	D <= '0';
	wait for 1 ns;

	A <= '0';
	B <= '0';
	C <= '1';
	D <= '1';
	wait for 1 ns;

	A <= '0';
	B <= '0';
	C <= '1';
	D <= '0';
	wait for 1 ns;

	A <= '0';
	B <= '0';
	C <= '0';
	D <= '1';
	wait for 1 ns;

	A <= '0';
	B <= '0';
	C <= '0';
	D <= '0';
	wait for 1 ns;

	assert false report "Reached end of test";
	wait;

	end process;

end test;

textbook/chap_5/1b_case.vcd
$date
  Mon Sep 21 13:47:33 2020
$end
$version
  GHDL v0
$end
$timescale
  1 fs
$end
$scope module standard $end
$upscope $end
$scope module std_logic_1164 $end
$upscope $end
$scope module ex_1b_case_tb $end
$var reg 1 ! a $end
$var reg 1 " b $end
$var reg 1 # c $end
$var reg 1 $ d $end
$var reg 1 % f $end
$scope module exercise $end
$var reg 1 & a $end
$var reg 1 ' b $end
$var reg 1 ( c $end
$var reg 1 ) d $end
$var reg 1 * f $end
$var reg 4 + abcd[3:0] $end
$upscope $end
$upscope $end
$enddefinitions $end
#0
X!
X"
X#
X$
0%
X&
X'
X(
X)
0*
bXXXX +
#1000000
1!
1"
1#
1$
1&
1'
1(
1)
b1111 +
#2000000
0$
1%
0)
1*
b1110 +
#3000000
0#
1$
0%
0(
1)
0*
b1101 +
#4000000
0$
0)
b1100 +
#5000000
0"
1#
1$
1%
0'
1(
1)
1*
b1011 +
#6000000
0$
0)
b1010 +
#7000000
0#
1$
0%
0(
1)
0*
b1001 +
#8000000
0$
0)
b1000 +
#9000000
0!
1"
1#
1$
0&
1'
1(
1)
b0111 +
#10000000
0$
1%
0)
1*
b0110 +
#11000000
0#
1$
0%
0(
1)
0*
b0101 +
#12000000
0$
0)
b0100 +
#13000000
0"
1#
1$
1%
0'
1(
1)
1*
b0011 +
#14000000
0$
0)
b0010 +
#15000000
0#
1$
0%
0(
1)
0*
b0001 +
#16000000
0$
0)
b0000 +
